peekpy/__init__.py
peekpy/config/__init__.py
peekpy/config/settings.py
peekpy/core/__init__.py
peekpy/core/analyse.py
peekpy/core/analyzers/__init__.py
peekpy/core/analyzers/base_analyzer.py
peekpy/core/analyzers/call_counter.py
peekpy/core/analyzers/timer.py
peekpy/core/utils.py
peekpy/storage/__init__.py
peekpy/storage/stats_manager.py
peekpy/wrapper.py
peekpy-0.1.0a4.dist-info/LICENSE
peekpy-0.1.0a4.dist-info/METADATA
peekpy-0.1.0a4.dist-info/WHEEL
peekpy-0.1.0a4.dist-info/RECORD
