Metadata-Version: 2.3
Name: peekpy
Version: 0.1.0a4
Summary: 
License: Apache-2.0
Author: Gael
Author-email: prungael@gmail.com
Requires-Python: >=3.10,<4.0
Classifier: License :: OSI Approved :: Apache Software License
Classifier: Programming Language :: Python :: 3
Classifier: Programming Language :: Python :: 3.10
Classifier: Programming Language :: Python :: 3.11
Classifier: Programming Language :: Python :: 3.12
Classifier: Programming Language :: Python :: 3.13
